Project 3/psdsqrt.v
module psdsqrt(
                clock,                        //master clock rising edge
                reset,                        //synch reset active high
                start,                        //start a new square root, one clock cycle
                stop,                         //load output register, one clock pulse
                xin,                          //operand, unsigned integer 32 bits
                sqrt                          //sqrt(xin), unsigned integer 16 bits
);


//Parameters
parameter NBITSIN = 32;                       //alínea 5.1
parameter k = 8;                             //alínea 5.2  

//Inputs and outputs
input clock;                
input reset;                      
input start;                        
input stop;                         
input [NBITSIN+k-1:0] xin;                   
output reg [((NBITSIN)/2)-1:0] sqrt;

//Local register
reg signed [NBITSIN+k-1:0]        FF1;
reg signed [((NBITSIN+k)/2)-1:0]    tempsqrt,
                                shift_reg,
                                FF2;
reg signed                      comparator;


//Local wires
wire signed [NBITSIN+k-1:0]  sqtestsqrt;
wire signed [((NBITSIN+k)/2)-1:0] testsqrt;
wire [(k/2)-1:0]parte_frac;
wire [(NBITSIN+k)/2-1-(k/2):0] parte_inteira;

//Local register
reg signed [((NBITSIN+k)/2)-1:0] aux;


//---------------------------------------------------
// Square (result of 32 bits)
assign sqtestsqrt = testsqrt * testsqrt;                                 //sqtestsqrt has 40 bits


//---------------------------------------------------
// Initial flip-flop:
always@(posedge clock)                         
if(reset)
    FF1 <= {(NBITSIN+k){1'b0}};                
else
begin
    if(start & ((NBITSIN+(k/2)) > 4 && (NBITSIN+(k/2)) < 64))            //verifies if the number of bits of xin is > 4 and < 64 --> alínea 5.1                                                              
        FF1 <= xin << 8;                                                 //xin now will have 40 bits
end


//---------------------------------------------------
// Comparator
always @*
if (FF1 >= sqtestsqrt)                                                   //A >= B 
    comparator <= 1;
else
    comparator <= 0;


//---------------------------------------------------
// Flip-flop with 2 multiplexers (left input for the OR Gate)
always@(posedge clock)
if(reset)
    tempsqrt <= {(((NBITSIN+k)/2)){1'b0}};
else
begin
    if(start)
        tempsqrt <= {(((NBITSIN+k)/2)){1'b0}};
    else
        tempsqrt <= comparator ? testsqrt : tempsqrt;                   //second multiplexor
end


assign parte_frac = tempsqrt[(k/2)-1:0];
assign parte_inteira = tempsqrt[(((NBITSIN+k)/2)-1):(k/2)];

//---------------------------------------------------
// Flip-flop with stop as enable
always@(posedge clock)
if(reset)
    sqrt <= {(((NBITSIN+k)/2)){1'b0}};
else
if(stop)
begin
    if(parte_frac < 8)                                          //8d = 1000b
	    sqrt <= parte_inteira;
	else if(parte_frac == 8) 
	    sqrt <= (parte_inteira + parte_inteira[0]);
	else if (parte_frac >= 9) 
	    sqrt <= (parte_inteira+1);

end


//---------------------------------------------------
// OR Gate
assign testsqrt = tempsqrt | FF2;                               //testsqrt has 20 bits


//---------------------------------------------------
// Flip-flop with multiplexer & shift register (right input for the OR Gate)
always@(posedge clock)
/*
if(reset)
    sqrt <= {(NBITSIN)/2){1'b0}};
else
*/
begin
    if(start)                       
        FF2  <= {1'b1, {(((NBITSIN+k)/2)-1){1'b0}}};                                             
    else
        FF2 <= FF2 >> 1;
end


endmodule

Project 3/psdsqrt_tb.v
/* 
PSD 2021-2022

Lab 1 - Design and verification of a sequential square root calculator

	This Verilog code is property of University of Porto
	Its utilization beyond the scope of the course Digital Systems Design
	(Projeto de Sistemas Digitais) of the Master in Electrical 
	and Computer Engineering requires explicit authorization from the author.
	
	jca@fe.up.pt, April 2022
	
*/
`timescale 1ns / 1ns

module psdsqrt_tb;
 
initial
begin
  $dumpfile("mysimdata.vcd");// The filename with the waveform data
  $dumpvars(0, psdsqrt_tb); // The root node to dump end
end


// general parameters 
parameter CLOCK_PERIOD = 10;              // Clock period in ns
parameter MAX_SIM_TIME = 100_000_000;     // Set the maximum simulation time (time units=ns)

//Parameters defined by the user
parameter NBITSIN_tb = 32;                       //alínea 5.1
parameter k_tb = 8;                              //alínea 5.2  


// Registers for driving the inputs:
reg  clock, reset;
reg  start, stop;
reg  [NBITSIN_tb+k_tb-1:0] x;

// Wires to connect to the outputs:
wire [((NBITSIN_tb)/2)-1:0] sqrt;
//wire start, stop, busy;                         //alínea 5.3
/*
ext_controller #(.NBITSIN(NUM_BITS)
              ) 

      ext_controller_1    
		  ( 		
          .run(run),
				  .clock(clock), 
				  .reset(reset),
				  .busy(busy),
				  .start(start),
				  .stop(stop)
			);

*/

// Instantiate the module under verification:
psdsqrt #( .NBITSIN( NBITSIN_tb ),              //alínea 5.1
           .k( k_tb )                           //alínea 5.2
        )

      psdsqrt_1
      ( 
	      .clock(clock), // master clock, active in the positive edge
        .reset(reset), // master reset, synchronous and active high
		
        .start(start), // set to 1 during one clock cycle to start a sqrt
        .stop(stop),   // set to 1 during one clock cycle to load the output registers
		
        .xin(x),       // the operands
        .sqrt(sqrt)
      ); 
      
        
//---------------------------------------------------
// Setup initial signals
initial
begin
  clock = 1'b0;
  reset = 1'b0;
  x = 0;
  start = 1'b0;
  stop  = 1'b0;
end

//---------------------------------------------------
// generate a 50% duty-cycle clock signal
initial
begin  
  forever
    # (CLOCK_PERIOD / 2 ) clock = ~clock;
end

//---------------------------------------------------
// Apply the initial reset for 2 clock cycles:
initial
begin
  # (CLOCK_PERIOD/3) // wait a fraction of the clock period to 
                     // misalign the reset pulse with the clock edges:
  reset = 1;
  # (2 * CLOCK_PERIOD ) // apply the reset for 2 clock periods
  reset = 0;
end

//---------------------------------------------------
// Set the maximum simulation time:
initial
begin
  # ( MAX_SIM_TIME )
  $stop;
end

//---------------------------------------------------
// The verification program (THIS IS TRUE A PROGRAM!)
integer i;
initial
begin

  // Wait 10 clock periods
  #( 10*CLOCK_PERIOD );

  execsqrt( 123456 );
  $display("Golden: %d, sqrt = %d",  golden_sqrt( 123456 ), sqrt);  

  execsqrt( 109876 );
  $display("Golden: %d, sqrt = %d",  golden_sqrt( 109876 ), sqrt);  

  execsqrt( 543210 );
  $display("Golden: %d, sqrt = %d",  golden_sqrt( 543210 ), sqrt);  

  execsqrt( 12 );
  $display("Golden: %d, sqrt = %d",  golden_sqrt( 12 ), sqrt);  

  execsqrt( 13 );
  $display("Golden: %d, sqrt = %d",  golden_sqrt( 13 ), sqrt);  

  execsqrt( 1057 );
  $display("Golden: %d, sqrt = %d",  golden_sqrt( 1057 ), sqrt);  

  execsqrt( 4291 );
  $display("Golden: %d, sqrt = %d",  golden_sqrt( 4291 ), sqrt);  
       
  #( 10*CLOCK_PERIOD );
  $stop;  
  //$finish
  
end


//---------------------------------------------------
// Simulate the sequential controller to perform a square root.
task execsqrt;
input [NBITSIN_tb:0] xin;
begin
  x = xin;   // Apply operands


  @(negedge clock);
  start = 1'b1;       // Assert start
  @(negedge clock );
  start = 1'b0;  
  repeat ((NBITSIN_tb+k_tb)/2) @(posedge clock);                                 //alterado
  @(negedge clock);
  stop = 1'b1;        // Assert stop
  @(negedge clock);
  stop = 1'b0;
  @(negedge clock);

end  
endtask



//---------------------------------------------------
// A Verilog function implementing the same SQRT algorithm
// This is the "golden" function whose result should be exact
// bit by bit with the result created by your circuit.
// Note this does not include the rounding process nor
// supports the parameterization for different number of bits
function [15:0] golden_sqrt( input [31:0] xin );
reg   [15:0] mask;
reg   [15:0] temproot;
integer i;
begin
  mask = 16'b1000_0000_0000_0000;
  temproot = 0;
  for (i=0; i<16; i=i+1 )
  begin
    if (  xin >= ( temproot | mask ) * (temproot | mask ) )
      temproot = temproot | mask;
    mask = mask >> 1;
  end
  golden_sqrt = temproot;
end
endfunction

endmodule

Project 3/mysimdata.vcd
$date
	Thu Apr 28 21:35:04 2022
$end
$version
	Icarus Verilog
$end
$timescale
	1ns
$end
$scope module psdsqrt_tb $end
$var wire 26 ! sqrt [25:0] $end
$var reg 1 " clock $end
$var reg 1 # reset $end
$var reg 1 $ start $end
$var reg 1 % stop $end
$var reg 52 & x [51:0] $end
$scope function golden_sqrt $end
$var reg 16 ' mask [15:0] $end
$var reg 16 ( temproot [15:0] $end
$var reg 32 ) xin [31:0] $end
$var integer 32 * i [31:0] $end
$upscope $end
$scope module psdsqrt_1 $end
$var wire 1 " clock $end
$var wire 1 # reset $end
$var wire 1 $ start $end
$var wire 1 % stop $end
$var wire 26 + testsqrt [25:0] $end
$var wire 52 , xin [51:0] $end
$var wire 52 - sqtestsqrt [51:0] $end
$var reg 52 . FF1 [51:0] $end
$var reg 26 / FF2 [25:0] $end
$var reg 1 0 comparator $end
$var reg 26 1 sqrt [25:0] $end
$var reg 26 2 tempsqrt [25:0] $end
$upscope $end
$scope task execsqrt $end
$var reg 32 3 xin [31:0] $end
$upscope $end
$upscope $end
$enddefinitions $end
#0
$dumpvars
bx 3
bx 2
bx 1
x0
bx /
bx .
bx -
b0 ,
bx +
bx *
bx )
bx (
bx '
b0 &
0%
0$
0#
0"
bx !
$end
#3
1#
#5
00
b0 .
b0 2
b0 !
b0 1
1"
#10
0"
#15
1"
#20
0"
#23
0#
#25
b0xxxxxxxxxxxxxxxxxxxxxxxxx +
b0xxxxxxxxxxxxxxxxxxxxxxxxx /
1"
#30
0"
#35
b0xxxxxxxxxxxxxxxxxxxxxxxx +
b0xxxxxxxxxxxxxxxxxxxxxxxx /
1"
#40
0"
#45
b0xxxxxxxxxxxxxxxxxxxxxxx +
b0xxxxxxxxxxxxxxxxxxxxxxx /
1"
#50
0"
#55
b0xxxxxxxxxxxxxxxxxxxxxx +
b0xxxxxxxxxxxxxxxxxxxxxx /
1"
#60
0"
#65
b0xxxxxxxxxxxxxxxxxxxxx +
b0xxxxxxxxxxxxxxxxxxxxx /
1"
#70
0"
#75
b0xxxxxxxxxxxxxxxxxxxx +
b0xxxxxxxxxxxxxxxxxxxx /
1"
#80
0"
#85
b0xxxxxxxxxxxxxxxxxxx +
b0xxxxxxxxxxxxxxxxxxx /
1"
#90
0"
#95
b0xxxxxxxxxxxxxxxxxx +
b0xxxxxxxxxxxxxxxxxx /
1"
#100
1$
0"
b11110001001000000 &
b11110001001000000 ,
b11110001001000000 3
#105
b1000000000000000000000000000000 -
b1000000000000000 +
b11110001001000000 .
b1000000000000000 /
1"
#110
0$
0"
#115
b10000000000000000000000000000 -
b100000000000000 +
b100000000000000 /
1"
#120
0"
#125
b100000000000000000000000000 -
b10000000000000 +
b10000000000000 /
1"
#130
0"
#135
b1000000000000000000000000 -
b1000000000000 +
b1000000000000 /
1"
#140
0"
#145
b10000000000000000000000 -
b100000000000 +
b100000000000 /
1"
#150
0"
#155
b100000000000000000000 -
b10000000000 +
b10000000000 /
1"
#160
0"
#165
b1000000000000000000 -
b1000000000 +
b1000000000 /
1"
#170
0"
#175
10
b10000000000000000 -
b100000000 +
b100000000 /
1"
#180
0"
#185
00
b100100000000000000 -
b110000000 +
b100000000 2
b10000000 /
1"
#190
0"
#195
10
b11001000000000000 -
b101000000 +
b1000000 /
1"
#200
0"
#205
00
b11110010000000000 -
b101100000 +
b101000000 2
b100000 /
1"
#210
0"
#215
10
b11011100100000000 -
b101010000 +
b10000 /
1"
#220
0"
#225
b11100111001000000 -
b101011000 +
b101010000 2
b1000 /
1"
#230
0"
#235
b11101100100010000 -
b101011100 +
b100 /
b101011000 2
1"
#240
0"
#245
b11101111010000100 -
b101011110 +
b101011100 2
b10 /
1"
#250
0"
#255
b11110000101000001 -
b101011111 +
b1 /
b101011110 2
1"
#260
0"
#265
b101011111 2
b0 /
1"
#270
1%
0"
#275
b101011111 !
b101011111 1
1"
#280
0%
0"
#285
1"
#290
b10000 *
b101011111 (
b0 '
b11110001001000000 )
0"
